core_framework/__init__.py
core_framework/crawlers.py
core_framework/db_engine.py
core_framework/deploy.py
core_framework/parsers.py
core_framework/proxy_client.py
core_framework/proxy_dist.py
core_framework/proxy_server.py
core_framework/request.py
core_framework/settings.py
core_framework/sql.py
core_framework/tor_network.py
core_framework/user_agent.py
core_framework/tables/__init__.py
core_framework/tables/bases.py
core_framework/tables/descriptors.py
core_framework/tables/proxies.py
core_framework/tables/tables.py
core_framework/tables/tors.py
crawler_framework-0.3.4.data/scripts/config.py
crawler_framework-0.3.4.data/scripts/configv3.py
crawler_framework-0.3.4.data/scripts/dbconfigv3.py
examples/__init__.py
examples/crawler.py
scripts/__init__.py
scripts/config.py
scripts/configv3.py
crawler_framework-0.3.4.dist-info/METADATA
crawler_framework-0.3.4.dist-info/WHEEL
crawler_framework-0.3.4.dist-info/top_level.txt
crawler_framework-0.3.4.dist-info/RECORD
