Metadata-Version: 2.1
Name: crawler-framework
Version: 0.3.4
Summary: Framework for crawling
Home-page: UNKNOWN
Author: Dragan Matesic
Author-email: dragan.matesic@gmail.com
License: MIT
Platform: UNKNOWN
Requires-Dist: cython
Requires-Dist: SQLAlchemy
Requires-Dist: pandas
Requires-Dist: requests
Requires-Dist: bs4
Requires-Dist: stem
Requires-Dist: pyodbc
Requires-Dist: psycopg2
Requires-Dist: cx-oracle
Requires-Dist: aiohttp-socks
Requires-Dist: aiohttp
Requires-Dist: psutil
Requires-Dist: virtualenv
Requires-Dist: lxml
Requires-Dist: pysocks
